NatNetClient-0.8.3.dist-info/METADATA
NatNetClient-0.8.3.dist-info/RECORD
NatNetClient-0.8.3.dist-info/WHEEL
NatNetClient-0.8.3.dist-info/top_level.txt
natnetclient/__init__.py
natnetclient/natnet.py
natnetclient/tracker.py
tests/__init__.py
tests/test_imports.py
